dyn2py/__init__.py
dyn2py/__main__.py
dyn2py/files.py
dyn2py/options.py
dyn2py-0.4.1.dist-info/LICENSE
dyn2py-0.4.1.dist-info/METADATA
dyn2py-0.4.1.dist-info/WHEEL
dyn2py-0.4.1.dist-info/entry_points.txt
dyn2py-0.4.1.dist-info/top_level.txt
dyn2py-0.4.1.dist-info/RECORD
