Metadata-Version: 2.1
Name: dyn2py
Version: 0.4.1
Summary: Extract python code from Dynamo graphs
Author-email: infeeeee <gyetpet@mailbox.org>
Maintainer-email: infeeeee <gyetpet@mailbox.org>
License: GNU GENERAL PUBLIC LICENSE
Project-URL: documentation, https://infeeeee.github.io/dyn2py
Project-URL: repository, https://github.com/infeeeee/dyn2py
Project-URL: changelog, https://github.com/infeeeee/dyn2py/releases
Keywords: dynamo,dyn,visual programming
Classifier: Development Status :: 4 - Beta
Classifier: Environment :: Console
Classifier: License :: OSI Approved :: GNU General Public License v3 (GPLv3)
Requires-Python: >=3.8
License-File: LICENSE
Requires-Dist: importlib-metadata
Requires-Dist: pathvalidate
Requires-Dist: simplejson
Provides-Extra: build
Requires-Dist: pyinstaller ; extra == 'build'
Provides-Extra: doc
Requires-Dist: pdoc ; extra == 'doc'
